easyFileShare/FS.py
easyFileShare/__init__.py
easyFileShare-0.22.dist-info/LICENSE
easyFileShare-0.22.dist-info/METADATA
easyFileShare-0.22.dist-info/WHEEL
easyFileShare-0.22.dist-info/top_level.txt
easyFileShare-0.22.dist-info/RECORD
