Metadata-Version: 2.1
Name: easyFileShare
Version: 0.22
Summary: This module to used to quickly add network file sharing capabilities to a python project
Home-page: https://github.com/harshnative/easyFileShare_module
Author: Harsh Native
Author-email: Harshnative@gmail.com
License: UNKNOWN
Platform: UNKNOWN
Classifier: Programming Language :: Python :: 3
Classifier: License :: OSI Approved :: MIT License
Classifier: Operating System :: OS Independent
Requires-Python: >=3.6
Requires-Dist: pyftpdlib
